parallelizer/__init__.py
parallelizer/executor.py
parallelizer/executor_event.py
parallelizer/parallelizer.py
parallelizer/process_parallelizer.py
parallelizer/result.py
parallelizer/task.py
parallelizer/thread_parallelizer.py
parallelizer/tools.py
parallelizer/test/__init__.py
parallelizer/test/test_power.py
parallelizer-0.1.dist-info/LICENSE.txt
parallelizer-0.1.dist-info/METADATA
parallelizer-0.1.dist-info/WHEEL
parallelizer-0.1.dist-info/top_level.txt
parallelizer-0.1.dist-info/RECORD
