Metadata-Version: 2.1
Name: parallelizer
Version: 0.1
Summary: Parallel execution of your tasks simplified! Analog to concurrent.futures executors.
Home-page: https://github.com/jpleorx/parallelizer
Author: Leo Ertuna
Author-email: leo.ertuna@gmail.com
License: MIT
Download-URL: https://pypi.org/project/parallelizer/
Keywords: executor,thread,process,parallel,multiprocessing,multithreading
Platform: UNKNOWN
Requires-Dist: simplestr
